athena/AtConstants.py
athena/AtCore.py
athena/AtExceptions.py
athena/AtStatus.py
athena/AtTests.py
athena/AtUtils.py
athena/__init__.py
athena/examples/__init__.py
athena/examples/blueprint/__init__.py
athena/examples/blueprint/exampleBlueprint.py
athena/examples/process/__init__.py
athena/examples/process/exampleProcess.py
athena/software/__init__.py
athena/software/atBlender.py
athena/software/atHoudini.py
athena/software/atMaya.py
athena/software/atStandalone.py
athena/software/atUnrealEngine.py
athena_sanity-1.0.0b0.dist-info/LICENSE
athena_sanity-1.0.0b0.dist-info/METADATA
athena_sanity-1.0.0b0.dist-info/WHEEL
athena_sanity-1.0.0b0.dist-info/top_level.txt
athena_sanity-1.0.0b0.dist-info/RECORD
