Metadata-Version: 2.1
Name: athena-sanity
Version: 1.0.0b0
Summary: Open Source Sanity Checking framework
Home-page: https://github.com/gpijat/athena
Author: Gregory Pijat
Author-email: pijat.gregory@gmail.com
Project-URL: Bug Tracker, https://github.com/gpijat/athena/issues
Classifier: Programming Language :: Python :: 3
Classifier: License :: OSI Approved :: GNU General Public License v3 (GPLv3)
Classifier: Operating System :: OS Independent
Requires-Python: >=3.7
License-File: LICENSE
